wllutils/__init__.py
wllutils/evaluate.py
wllutils/read_df.py
wllutils/wll_cmd.py
wllutils-0.0.8.1.dist-info/METADATA
wllutils-0.0.8.1.dist-info/WHEEL
wllutils-0.0.8.1.dist-info/top_level.txt
wllutils-0.0.8.1.dist-info/RECORD
