Metadata-Version: 2.1
Name: wllutils
Version: 0.0.8.1
Summary: utils of wll
Home-page: UNKNOWN
Author: weiliulei
Author-email: 18500964455@163.com
Maintainer: weiliulei
Maintainer-email: 18500964455@163.com
License: MIT
Platform: all
Requires-Dist: pandas
Requires-Dist: numpy
Requires-Dist: tqdm
Requires-Dist: scikit-learn
